{
  "chapter": 1,
  "title": "Os Karas",
  "clozes": [
    {
      "id": 1,
      "text": "Miguel convoca o grupo secreto mostrando a letra _____ gravada na palma da mão.",
      "blank": "K",
      "hint": "Primeira letra do nome do grupo"
    },
    {
      "id": 2,
      "text": "Para abandonar o ensaio de teatro, Calu alegou estar com uma forte _____.",
      "blank": "enxaqueca",
      "hint": "Tipo de dor de cabeça intensa"
    },
    {
      "id": 3,
      "text": "Crânio estava jogando uma partida de _____ quando recebeu a convocação de emergência.",
      "blank": "xadrez",
      "hint": "Jogo de tabuleiro estratégico"
    },
    {
      "id": 4,
      "text": "Ao ver o sinal de Miguel, Crânio derrubou o próprio _____ e abandonou a partida.",
      "blank": "rei",
      "hint": "Peça principal do jogo de xadrez"
    },
    {
      "id": 5,
      "text": "Magrí fingiu ter lesionado o _____ para poder sair do treino de vôlei.",
      "blank": "tornozelo",
      "hint": "Articulação do pé com a perna"
    },
    {
      "id": 6,
      "text": "O esconderijo secreto dos Karas fica no _____ do vestiário do Colégio Elite.",
      "blank": "forro",
      "hint": "Parte superior / sótão acima do teto"
    },
    {
      "id": 7,
      "text": "Para entrar no esconderijo, os membros sobem por um _____ localizado no quarto de vassouras.",
      "blank": "alçapão",
      "hint": "Porta de alçapão no teto"
    },
    {
      "id": 8,
      "text": "Miguel espalhou recortes de _____ no chão do esconderijo para mostrar aos amigos.",
      "blank": "jornais",
      "hint": "Mídia impressa sobre notícias"
    },
    {
      "id": 9,
      "text": "A convocação de Miguel era uma emergência _____ para investigar o sumiço dos alunos.",
      "blank": "máxima",
      "hint": "Nível mais alto de alerta do grupo"
    },
    {
      "id": 10,
      "text": "Crânio costuma tocar sua _____ de boca em momentos de profunda reflexão.",
      "blank": "gaita",
      "hint": "Instrumento musical de sopro pequeno"
    }
  ]
}
